amazon_sagemaker_sql_magic/__init__.py
amazon_sagemaker_sql_magic/exceptions.py
amazon_sagemaker_sql_magic/sql_magic.py
amazon_sagemaker_sql_magic/utils/__init__.py
amazon_sagemaker_sql_magic/utils/constants.py
amazon_sagemaker_sql_magic/utils/output_format_arguments_processor.py
amazon_sagemaker_sql_magic/utils/string_utils.py
amazon_sagemaker_sql_magic-0.1.1.dist-info/LICENSE
amazon_sagemaker_sql_magic-0.1.1.dist-info/METADATA
amazon_sagemaker_sql_magic-0.1.1.dist-info/NOTICE
amazon_sagemaker_sql_magic-0.1.1.dist-info/WHEEL
amazon_sagemaker_sql_magic-0.1.1.dist-info/top_level.txt
amazon_sagemaker_sql_magic-0.1.1.dist-info/RECORD
