Metadata-Version: 2.1
Name: amazon-sagemaker-sql-magic
Version: 0.1.1
Summary: SageMaker SQL Magic library
Author: Amazon Web Services
License: Apache License
Project-URL: homepage, https://aws.amazon.com/sagemaker
Classifier: Intended Audience :: Developers
Classifier: Intended Audience :: Science/Research
Classifier: License :: OSI Approved :: Apache Software License
Classifier: Programming Language :: Python
Classifier: Programming Language :: Python :: 3.8
Classifier: Programming Language :: Python :: 3.9
Classifier: Programming Language :: Python :: 3.10
Classifier: Programming Language :: Python :: 3.11
Requires-Python: >=3.8
License-File: LICENSE
License-File: NOTICE
Requires-Dist: pandas
Requires-Dist: IPython
Requires-Dist: sqlparse ==0.4.*
Requires-Dist: amazon-sagemaker-sql-execution <1,>=0.0.7
Provides-Extra: all
Requires-Dist: amazon-sagemaker-sql-magic[dev,flake8,pydocstyle,pylint,test,twine] ; extra == 'all'
Requires-Dist: amazon-sagemaker-sql-execution[all] <1,>=0.0.7 ; extra == 'all'
Provides-Extra: dev
Requires-Dist: black ; extra == 'dev'
Requires-Dist: build ; extra == 'dev'
Provides-Extra: flake8
Requires-Dist: flake8 ==4.0.1 ; extra == 'flake8'
Requires-Dist: flake8-future-import ==0.4.6 ; extra == 'flake8'
Provides-Extra: pydocstyle
Requires-Dist: pydocstyle ==6.1.1 ; extra == 'pydocstyle'
Provides-Extra: pylint
Requires-Dist: pylint ==2.6.2 ; extra == 'pylint'
Requires-Dist: astroid ==2.4.2 ; extra == 'pylint'
Provides-Extra: test
Requires-Dist: pytest ; extra == 'test'
Requires-Dist: tox ==4.11.4 ; extra == 'test'
Requires-Dist: parameterized ; extra == 'test'
Requires-Dist: coverage ; extra == 'test'
Requires-Dist: pytest-cov ; extra == 'test'
Requires-Dist: pytest-timeout ; extra == 'test'
Requires-Dist: boto3 ; extra == 'test'
Provides-Extra: twine
Requires-Dist: twine ==3.8.0 ; extra == 'twine'
Requires-Dist: packaging ; extra == 'twine'
